{"cameraMode":{"drawMode":0,"name":"Shaded","section":"Shading Mode"},"sceneLighting":true,"audioPlay":false,"sceneViewState":{"m_AlwaysRefresh":false,"showFog":true,"showSkybox":true,"showFlares":true,"showImageEffects":true,"showParticleSystems":true,"showVisualEffectGraphs":true,"m_FxEnabled":true},"in2DMode":false,"pivot":{"x":1.2013988494873047,"y":2.1329243183135988,"z":-2.89798641204834},"rotation":{"x":-0.10044358670711518,"y":0.3674536943435669,"z":-0.03995400667190552,"w":-0.923743486404419},"size":6.429994106292725,"orthographic":false}